srcomp/__init__.py
srcomp/live/__init__.py
srcomp/live/_version.py
srcomp/live/main.py
srcomp/live/osc.py
srcomp/live/test_server.py
srcomp/live/time_fetch.py
srcomp/live/utils.py
srcomp_live-1.2.0.dist-info/licenses/LICENSE
srcomp_live-1.2.0.dist-info/METADATA
srcomp_live-1.2.0.dist-info/WHEEL
srcomp_live-1.2.0.dist-info/entry_points.txt
srcomp_live-1.2.0.dist-info/top_level.txt
srcomp_live-1.2.0.dist-info/RECORD
