Metadata-Version: 2.4
Name: srcomp-live
Version: 1.2.0
Summary: An interposer between the SRComp REST API and OSC controlled devices.
Author: Will Barber
License: MIT License
Project-URL: Repository, https://github.com/WillB97/srcomp-live
Requires-Python: >=3.8
License-File: LICENSE
Requires-Dist: requests<3,>=2.32.3
Requires-Dist: python-osc<2,>=1.8.3
Provides-Extra: dev
Requires-Dist: poethepoet<1,>=0.0.1; extra == "dev"
Requires-Dist: ruff<0.4,>=0.3.0; extra == "dev"
Requires-Dist: mypy==1.9.0; extra == "dev"
Requires-Dist: build; extra == "dev"
Requires-Dist: types-requests; extra == "dev"
Requires-Dist: types-PyYAML<7,>=6; extra == "dev"
Provides-Extra: yaml
Requires-Dist: PyYAML<7,>=6; extra == "yaml"
Dynamic: license-file
